boaapi/__init__.py
boaapi/boa_client.py
boaapi/boa_client.pyi
boaapi/job_handle.py
boaapi/job_handle.pyi
boaapi/py.typed
boaapi/status.py
boaapi/status.pyi
boaapi/util.py
boaapi/util.pyi
boa_api-0.1.14.dist-info/LICENSE
boa_api-0.1.14.dist-info/METADATA
boa_api-0.1.14.dist-info/WHEEL
boa_api-0.1.14.dist-info/top_level.txt
boa_api-0.1.14.dist-info/RECORD
