Metadata-Version: 2.1
Name: boa-api
Version: 0.1.14
Summary: Client API for using the Boa infrastructure
Home-page: https://github.com/boalang/api-python
Author: Boa Project
Author-email: boasupport@iastate.edu
Classifier: Programming Language :: Python :: 3
Classifier: License :: OSI Approved :: Apache Software License
Classifier: Intended Audience :: Education
Classifier: Intended Audience :: Science/Research
Classifier: Operating System :: OS Independent
Requires-Python: >=3.5
License-File: LICENSE
